ito_diffusions/__init__.py
ito_diffusions/ito_diffusion.py
ito_diffusions/ito_diffusion_1d.py
ito_diffusions/ito_diffusion_multi_d.py
ito_diffusions/ito_diffusion_sheaf.py
ito_diffusions/noise.py
ito_diffusions/pdmp.py
ito_diffusions/pdmp_1d.py
ito_diffusions/saw.py
ito_diffusions/sle.py
ito_diffusions/time_series.py
ito_diffusions-1.4.1.dist-info/LICENSE.txt
ito_diffusions-1.4.1.dist-info/METADATA
ito_diffusions-1.4.1.dist-info/WHEEL
ito_diffusions-1.4.1.dist-info/top_level.txt
ito_diffusions-1.4.1.dist-info/RECORD
