Metadata-Version: 2.1
Name: ito-diffusions
Version: 1.4.1
Summary: Library for stochastic process simulation
Home-page: https://github.com/sauxpa/ito_diffusions
Author: Patrick Saux
Author-email: patrick.jr.saux@gmail.com
Requires-Python: >=3.6
License-File: LICENSE.txt
Requires-Dist: numpy
Requires-Dist: scipy
Requires-Dist: pandas
Requires-Dist: mpmath
Requires-Dist: tqdm
